{
  "task_id": 784,
  "code": "def candidate(nums):\n    # Initialize variables to store the first even and odd numbers\n    first_even = None\n    first_odd = None\n\n    # Iterate through the list and identify even and odd numbers\n    for num in nums:\n        if num % 2 == 0:\n            if first_even is None:\n                first_even = num\n        else:\n            if first_odd is None:\n                first_odd = num\n\n    # Return the product of first even and odd number (or None if not found)\n    return first_even * first_odd if first_even is not None and first_odd is not None else None",
  "explanation": "Explanation\n----------\n\nThe given code attempts to find the product of the first even and odd numbers in a list. However, it has several issues. The main problem is that the variable names are not descriptive, which makes the code harder to understand. Additionally, there's an attempt to run the function as a script with `python`, but Python doesn't recognize this syntax. The code should be treated as a standalone function definition.\n\nCode",
  "num_iterations": 3,
  "error_msg": null,
  "success": true
}