{
  "task_id": 249,
  "code": "python\ndef candidate(list1, list2):\n    # Convert input lists to sets to remove duplicates and improve lookup efficiency\n    set1 = set(list1)\n    set2 = set(list2)\n\n    # Use a set comprehension to find the intersection of the two sets without duplicates\n    # Filter out elements that are not common in both sets\n    intersection = {element for element in set1 if element in set2}\n\n    # Return the result as a list\n    return list(intersection)",
  "explanation": "Explanation\n-----------\n\nThe original code attempts to find the intersection of two arrays using sets and a set comprehension. However, it includes an incorrect function definition that references itself (`python`) and does not contain any meaningful comments.\n\nTo correct the code, we will define a new function named `candidate` that takes two lists as input, converts them to sets to remove duplicates and improve lookup efficiency, uses a set comprehension to find the intersection of the two sets without duplicates, and returns the result as a list.\n\nCode\n-----",
  "num_iterations": 6,
  "error_msg": "Traceback (most recent call last):\n  File \"/home/runner/sandbox/temp_code.py\", line 1, in <module>\n    python\nNameError: name 'python' is not defined\n\n",
  "success": false
}